pgedl/__init__.py
pgedl/pgedl.py
pgedl-0.1.1.dist-info/entry_points.txt
pgedl-0.1.1.dist-info/WHEEL
pgedl-0.1.1.dist-info/METADATA
pgedl-0.1.1.dist-info/RECORD
