Metadata-Version: 2.1
Name: pgedl
Version: 0.1.1
Summary: 
Author: myyc
Author-email: myyc@domain.xxx
Requires-Python: >=3.8,<4.0
Classifier: Programming Language :: Python :: 3
Classifier: Programming Language :: Python :: 3.8
Requires-Dist: requests (>=2.23.0,<3.0.0)
